smithwilson2/__init__.py
smithwilson2/smithwilson2.py
smithwilson2-0.0.1.dist-info/METADATA
smithwilson2-0.0.1.dist-info/WHEEL
smithwilson2-0.0.1.dist-info/licenses/LICENSE
smithwilson2-0.0.1.dist-info/RECORD
