Metadata-Version: 2.3
Name: smithwilson2
Version: 0.0.1
Summary: A package to extrapolate forward rates using the EIOPA Smith-Wilson method.
Project-URL: Homepage, https://github.com/deridderk/smithwilson2
Author-email: Kilian de Ridder <kilian.deridder@gmx.de>
License-File: LICENSE
Classifier: License :: OSI Approved :: MIT License
Classifier: Operating System :: OS Independent
Classifier: Programming Language :: Python :: 3
Requires-Python: >=3.8
